multibeast/__init__.py
multibeast/builder.py
multibeast/version.py
multibeast/agents/__init__.py
multibeast/agents/example_agent.py
multibeast/agents/losses.py
multibeast/agents/multihydra.py
multibeast/agents/policy_nets.py
multibeast/agents/record_utils.py
multibeast/agents/impala/__init__.py
multibeast/agents/impala/impala.py
multibeast/agents/impala/impala_net.py
multibeast/agents/impala/losses.py
multibeast/agents/impala/vtrace.py
multibeast/agents/ppo/__init__.py
multibeast/agents/ppo/ppo.py
multibeast/agents/ppo/ppo_net.py
multibeast/distributions/__init__.py
multibeast/distributions/discretized_logistic_mixture.py
multibeast/distributions/gaussian_squashed_gaussian.py
multibeast/distributions/get_action_params.py
multibeast/distributions/multi_categorical.py
multibeast/distributions/normal_mixture.py
multibeast/distributions/squashed_diag_gaussian.py
multibeast/envpool/__init__.py
multibeast/envpool/envbatchstate.py
multibeast/envpool/envpool.py
multibeast/envpool/envstepper.py
multibeast/examples/__init__.py
multibeast/utils/__init__.py
multibeast/utils/registry.py
multibeast-0.0.1a1.dist-info/LICENSE
multibeast-0.0.1a1.dist-info/METADATA
multibeast-0.0.1a1.dist-info/WHEEL
multibeast-0.0.1a1.dist-info/top_level.txt
multibeast-0.0.1a1.dist-info/RECORD
