Metadata-Version: 2.1
Name: multibeast
Version: 0.0.1a1
Summary: UNKNOWN
Home-page: https://github.com/etaoxing/multibeast
Download-URL: https://github.com/etaoxing/multibeast/tags
Author: etaoxing
License: MIT
Platform: UNKNOWN
Classifier: License :: OSI Approved :: MIT License
Classifier: Programming Language :: Python :: 3
Requires-Python: >=3.7
License-File: LICENSE
Requires-Dist: torch (>=1.9.1)
Requires-Dist: hydra-core (>=1.0.0)
Requires-Dist: hydra-colorlog (>=1.0.0)
Requires-Dist: hydra-submitit-launcher (>=1.1.1)
Requires-Dist: wandb (>=0.10.31)
Requires-Dist: pyyaml
Requires-Dist: moolib
Requires-Dist: tinyspace
Requires-Dist: tabulate
Requires-Dist: coolname
Provides-Extra: all
Requires-Dist: pre-commit (>=2.0.1) ; extra == 'all'
Requires-Dist: black (>=19.10b0) ; extra == 'all'
Requires-Dist: flake8 (>=3.7) ; extra == 'all'
Requires-Dist: flake8-bugbear (>=20.1) ; extra == 'all'
Requires-Dist: flake8-docstrings (>=1.6.0) ; extra == 'all'
Requires-Dist: pytest (>=5.3) ; extra == 'all'
Requires-Dist: pytest-benchmark (>=3.1.0) ; extra == 'all'
Requires-Dist: pytest-order (>=1.0.1) ; extra == 'all'
Requires-Dist: pytest-cov ; extra == 'all'
Requires-Dist: pytest-xdist ; extra == 'all'
Requires-Dist: pyright ; extra == 'all'
Requires-Dist: isort (>=5.0) ; extra == 'all'
Requires-Dist: sphinx (==4.4.0) ; extra == 'all'
Requires-Dist: sphinx-autobuild ; extra == 'all'
Requires-Dist: myst-parser ; extra == 'all'
Requires-Dist: sphinxcontrib-spelling ; extra == 'all'
Requires-Dist: sphinx-autodoc-typehints ; extra == 'all'
Requires-Dist: sphinx-design ; extra == 'all'
Requires-Dist: sphinx-copybutton ; extra == 'all'
Requires-Dist: sphinx-inline-tabs ; extra == 'all'
Requires-Dist: sphinxcontrib-trio ; extra == 'all'
Requires-Dist: sphinxext-opengraph ; extra == 'all'
Requires-Dist: furo ; extra == 'all'
Provides-Extra: docs
Requires-Dist: sphinx (==4.4.0) ; extra == 'docs'
Requires-Dist: sphinx-autobuild ; extra == 'docs'
Requires-Dist: myst-parser ; extra == 'docs'
Requires-Dist: sphinxcontrib-spelling ; extra == 'docs'
Requires-Dist: sphinx-autodoc-typehints ; extra == 'docs'
Requires-Dist: sphinx-design ; extra == 'docs'
Requires-Dist: sphinx-copybutton ; extra == 'docs'
Requires-Dist: sphinx-inline-tabs ; extra == 'docs'
Requires-Dist: sphinxcontrib-trio ; extra == 'docs'
Requires-Dist: sphinxext-opengraph ; extra == 'docs'
Requires-Dist: furo ; extra == 'docs'
Provides-Extra: tests
Requires-Dist: pre-commit (>=2.0.1) ; extra == 'tests'
Requires-Dist: black (>=19.10b0) ; extra == 'tests'
Requires-Dist: flake8 (>=3.7) ; extra == 'tests'
Requires-Dist: flake8-bugbear (>=20.1) ; extra == 'tests'
Requires-Dist: flake8-docstrings (>=1.6.0) ; extra == 'tests'
Requires-Dist: pytest (>=5.3) ; extra == 'tests'
Requires-Dist: pytest-benchmark (>=3.1.0) ; extra == 'tests'
Requires-Dist: pytest-order (>=1.0.1) ; extra == 'tests'
Requires-Dist: pytest-cov ; extra == 'tests'
Requires-Dist: pytest-xdist ; extra == 'tests'
Requires-Dist: pyright ; extra == 'tests'
Requires-Dist: isort (>=5.0) ; extra == 'tests'
